[
    {
        "id": "Bk2ayPDBGEw",
        "parentid": "",
        "soap": "EMMY",
        "category": "C",
        "title": "Emmys General Hospital Montage",
        "date": "10/10/2010",
        "part": "1",
        "total": "1",
        "duration": "00:16",
        "channel": "luckibelle",
        "cateogry": "C"
    },
    {
        "id": "dR_puLWrWdo",
        "parentid": "",
        "soap": "EMMY",
        "category": "C",
        "title": "Susan Lucci, Erika Slezak, Mathison",
        "date": "06/17/2012",
        "part": "1",
        "total": "1",
        "duration": "3:43",
        "channel": "obsessedjarlenafan",
        "cateogry": "C"
    }
]